{
  "magnet": "MQXFA12b",
  "measurement": "cold_nominal",
  "reference_radius_mm": 50,
  "multipoles": [
    {
      "n": 3,
      "bn": -2.06,
      "an": -0.47
    },
    {
      "n": 4,
      "bn": 0.42,
      "an": -2.29
    },
    {
      "n": 5,
      "bn": -0.24,
      "an": -0.8
    },
    {
      "n": 6,
      "bn": -0.69,
      "an": 0.34
    },
    {
      "n": 7,
      "bn": 0.51,
      "an": 0.05
    },
    {
      "n": 8,
      "bn": 0.08,
      "an": -0.15
    },
    {
      "n": 9,
      "bn": 0.12,
      "an": 0.11
    },
    {
      "n": 10,
      "bn": -0.31,
      "an": -0.03
    }
  ]
}